pah/__init__.py
pah/cli.py
pah/gui.py
pah-1.3.2.dist-info/METADATA
pah-1.3.2.dist-info/WHEEL
pah-1.3.2.dist-info/entry_points.txt
pah-1.3.2.dist-info/licenses/LICENSE
pah-1.3.2.dist-info/RECORD
