Metadata-Version: 2.4
Name: pah
Version: 1.3.2
Summary: PDF Auto Highlighter
Project-URL: homepage, https://github.com/ras0q/pah
Project-URL: issues, https://github.com/ras0q/pah/issues
Project-URL: repository, https://github.com/ras0q/pah
Author: ras0q
License: MIT License
License-File: LICENSE
Requires-Python: >=3.13
Requires-Dist: pah-core==1.3.2
Provides-Extra: gui
Requires-Dist: pah-gui==1.3.2; extra == 'gui'
